tagcube
tagcube_cli
