Metadata-Version: 1.1
Name: tagcube-cli
Version: 1.0.7
Summary: CLI to launch web application security scans usingTagCube's REST API 
Home-page: https://github.com/tagcubeio/tagcube-cli/
Author: TagCube
Author-email: support@tagcube.io
License: GNU General Public License v2 (GPLv2)
Platform: Linux
Classifier: Development Status :: 5 - Production/Stable
Classifier: Intended Audience :: Developers
Classifier: License :: OSI Approved :: GNU General Public License v2 (GPLv2)
Classifier: Natural Language :: English
Classifier: Operating System :: POSIX :: Linux
Classifier: Programming Language :: Python
Classifier: Programming Language :: Python :: 2.7
Classifier: Topic :: System :: Monitoring
